{
  "_format": "hh-sol-cache-2",
  "files": {
    "C:\\Users\\Julius\\Desktop\\My Lab\\Lab_23\\TS\\crowdfunding\\web3\\contracts\\CrowdFunding.sol": {
      "lastModificationDate": 1677489097677,
      "contentHash": "e8fdeadabb0a3733138f3de1fea74e96",
      "sourceName": "contracts/CrowdFunding.sol",
      "solcConfig": {
        "version": "0.8.19",
        "settings": {
          "optimizer": {
            "enabled": false,
            "runs": 200
          },
          "outputSelection": {
            "*": {
              "*": [
                "abi",
                "evm.bytecode",
                "evm.deployedBytecode",
                "evm.methodIdentifiers",
                "metadata"
              ],
              "": [
                "ast"
              ]
            }
          }
        }
      },
      "imports": [],
      "versionPragmas": [
        "^0.8.19"
      ],
      "artifacts": [
        "CrowdFunding"
      ]
    }
  }
}
